apscheduler_bundle/__init__.py
apscheduler_bundle/apscheduler_bundle.py
apscheduler_bundle-1.1.2.dist-info/METADATA
apscheduler_bundle-1.1.2.dist-info/RECORD
apscheduler_bundle-1.1.2.dist-info/WHEEL
apscheduler_bundle-1.1.2.dist-info/top_level.txt
